{
  "brand": "sony",
  "description": "Common bloatware on Sony Xperia devices",
  "packages": [
    {
      "id": "com.sonymobile.music",
      "name": "Sony Music",
      "description": "Sony music player. Substitute: Spotify, VLC.",
      "risk": "safe"
    },
    {
      "id": "com.sonymobile.video",
      "name": "Sony Video",
      "description": "Sony video player. Substitute: VLC.",
      "risk": "safe"
    },
    {
      "id": "com.sonymobile.album",
      "name": "Sony Album (Gallery)",
      "description": "Sony photo gallery. Substitute: Google Photos.",
      "risk": "safe"
    },
    {
      "id": "com.sonymobile.androidapp.socialife",
      "name": "Socialife",
      "description": "Sony social media aggregator. Generally unused.",
      "risk": "safe"
    },
    {
      "id": "com.sonymobile.lifelog",
      "name": "Lifelog",
      "description": "Sony activity/fitness tracker.",
      "risk": "safe"
    },
    {
      "id": "com.sonymobile.remotemenu",
      "name": "Remote Menu",
      "description": "Smart remote control feature.",
      "risk": "safe"
    },
    {
      "id": "com.sonymobile.sketch",
      "name": "Sony Sketch",
      "description": "Sony drawing app.",
      "risk": "safe"
    },
    {
      "id": "com.sonymobile.androidapp.GA",
      "name": "Sony Game Enhancer",
      "description": "Gaming optimization tool from Sony.",
      "risk": "safe"
    },
    {
      "id": "com.sonymobile.conversations",
      "name": "Sony Conversations",
      "description": "Sony messaging app. Substitute: Google Messages.",
      "risk": "safe"
    },
    {
      "id": "com.sonymobile.xperiaservicescenter",
      "name": "Xperia Services Center",
      "description": "Sony device management and telemetry service.",
      "risk": "caution"
    },
    {
      "id": "com.sonymobile.android.persistentservice",
      "name": "Sony Persistent Service",
      "description": "Core Sony background service. Removal may affect Xperia features.",
      "risk": "never"
    }
  ]
}
